Metadata-Version: 2.1
Name: emgfit
Version: 0.5.0
Summary: Fitting of time-of-flight mass spectra with Hyper-EMG models
Home-page: https://github.com/RobbenRoll/emgfit
Author: Stefan Paul
Author-email: stefan.paul@triumf.ca
License: BSD (3-clause)
Classifier: Development Status :: 4 - Beta
Classifier: Natural Language :: English
Classifier: Programming Language :: Python :: 3
Requires-Python: >=3.8
License-File: LICENSE.txt
License-File: AUTHORS.rst
Requires-Dist: lmfit >=1.2.2
Requires-Dist: numpy >=1.18.1
Requires-Dist: scipy >=1.3.2
Requires-Dist: pandas >=1.2.2
Requires-Dist: matplotlib
Requires-Dist: docutils >=0.3
Requires-Dist: ipython >=7.19.0
Requires-Dist: ipykernel >=5.3.4
Requires-Dist: numdifftools >=0.9.39
Requires-Dist: jupyter
Requires-Dist: numba
Requires-Dist: mpmath
Requires-Dist: emcee >=3.0
Requires-Dist: corner
Requires-Dist: tqdm
Requires-Dist: h5py
Requires-Dist: xlsxwriter >=1.2.8
Requires-Dist: xlrd >=1.0.0
Requires-Dist: openpyxl
Requires-Dist: termcolor
Requires-Dist: joblib
Requires-Dist: dill
Requires-Dist: multiprocess
Requires-Dist: pywin32 >=301 ; sys_platform == "win32"
